odoo_auth/__init__.py
odoo_auth/backends.py
odoo_auth/settings.py
django_odoo_auth-1.0.1.1.dist-info/LICENSE
django_odoo_auth-1.0.1.1.dist-info/METADATA
django_odoo_auth-1.0.1.1.dist-info/WHEEL
django_odoo_auth-1.0.1.1.dist-info/top_level.txt
django_odoo_auth-1.0.1.1.dist-info/RECORD
