Metadata-Version: 2.1
Name: django-odoo-auth
Version: 1.0.1.1
Summary: Custom django auth backend for authorization via odoo
Home-page: https://github.com/w0rng/django-odoo-auth
Author: w0rng, Julien DRECQ
License: Apache-2.0 License
Platform: UNKNOWN
Classifier: Environment :: Web Environment
Classifier: Framework :: Django
Classifier: Intended Audience :: Developers
Classifier: License :: OSI Approved :: Apache Software License
Classifier: Operating System :: OS Independent
Classifier: Programming Language :: Python :: 3.9
Classifier: Topic :: Internet :: WWW/HTTP
Classifier: Topic :: Internet :: WWW/HTTP :: Dynamic Content
License-File: LICENSE
Requires-Dist: django
